{"lastUsed":1581483728005,"path":"D:\/dev\/yoshino","projectCount":5,"recentFiles":[{"path":"\/javabook\/src\/javabook\/c6","parentWorkspace":"D:\/dev","name":"Ch6Ex2.java","lastModified":1580880241923,"locationURI":"file:\/D:\/dev\/javabook\/src\/javabook\/c6\/Ch6Ex2.java"},{"path":"\/vavo\/src\/main\/webapp\/WEB-INF\/views","parentWorkspace":"D:\/dev\/yoshino","name":"main.jsp","lastModified":1581483664317,"locationURI":"file:\/D:\/dev\/yoshino\/vavo\/src\/main\/webapp\/WEB-INF\/views\/main.jsp"},{"path":"\/vavo\/src\/main\/webapp\/WEB-INF\/views","parentWorkspace":"D:\/dev","name":"home.jsp","lastModified":1581483570447,"locationURI":"file:\/D:\/dev\/vavo\/src\/main\/webapp\/WEB-INF\/views\/home.jsp"},{"path":"\/javabook\/src\/javabook\/ch11","parentWorkspace":"D:\/dev\/yoshino","name":"C11ex10.java","lastModified":1581401036939,"locationURI":"file:\/D:\/dev\/yoshino\/javabook\/src\/javabook\/ch11\/C11ex10.java"},{"path":"\/javabook\/src\/javabook\/ch11","parentWorkspace":"D:\/dev\/yoshino","name":"C11ex4.java","lastModified":1581384359379,"locationURI":"file:\/D:\/dev\/yoshino\/javabook\/src\/javabook\/ch11\/C11ex4.java"},{"path":"\/osawa\/src\/mimina","parentWorkspace":"D:\/dev","name":"GUGUGU.java","lastModified":1580283559844,"locationURI":"file:\/D:\/dev\/osawa\/src\/mimina\/GUGUGU.java"},{"path":"\/javachobo\/src\/javachobo\/ch6","parentWorkspace":"D:\/dev","name":"Tvtes3.java","lastModified":1580437207668,"locationURI":"file:\/D:\/dev\/javachobo\/src\/javachobo\/ch6\/Tvtes3.java"},{"path":"\/javachobo\/src\/javachobo\/ch13","parentWorkspace":"D:\/dev\/yoshino","name":"Tex4.java","lastModified":1581394139501,"locationURI":"file:\/D:\/dev\/yoshino\/javachobo\/src\/javachobo\/ch13\/Tex4.java"},{"path":"\/javabook\/src\/javabook\/c5","parentWorkspace":"D:\/dev","name":"User.java","lastModified":1580700115429,"locationURI":"file:\/D:\/dev\/javabook\/src\/javabook\/c5\/User.java"},{"path":"\/osawa\/src\/mimina","parentWorkspace":"D:\/dev","name":"Calltes.java","lastModified":1580276036525,"locationURI":"file:\/D:\/dev\/osawa\/src\/mimina\/Calltes.java"},{"path":"\/javabook\/src\/javabook\/c8","parentWorkspace":"D:\/dev","name":"Ex1.java","lastModified":1580795391272,"locationURI":"file:\/D:\/dev\/javabook\/src\/javabook\/c8\/Ex1.java"},{"path":"\/javabook\/src\/javabook\/c8","parentWorkspace":"D:\/dev","name":"Ch6Ex9.java","lastModified":1580949636759,"locationURI":"file:\/D:\/dev\/javabook\/src\/javabook\/c8\/Ch6Ex9.java"},{"path":"\/javabook\/src\/javabook\/ch7","parentWorkspace":"D:\/dev","name":"C7ex6.java","lastModified":1581321635573,"locationURI":"file:\/D:\/dev\/javabook\/src\/javabook\/ch7\/C7ex6.java"},{"path":"\/test\/src\/sv","parentWorkspace":"D:\/dev\/yoshino","name":"Grp.java","lastModified":1581391851226,"locationURI":"file:\/D:\/dev\/yoshino\/test\/src\/sv\/Grp.java"},{"path":"\/javabook\/src\/javabook\/ch7","parentWorkspace":"D:\/dev","name":"C7ex3.java","lastModified":1581300017507,"locationURI":"file:\/D:\/dev\/javabook\/src\/javabook\/ch7\/C7ex3.java"},{"path":"\/javabook\/src\/javabook\/ch12","parentWorkspace":"D:\/dev\/yoshino","name":"MCcont.java","lastModified":1581479986522,"locationURI":"file:\/D:\/dev\/yoshino\/javabook\/src\/javabook\/ch12\/MCcont.java"},{"path":"\/javachobo\/src\/javachobo\/ch3","parentWorkspace":"D:\/dev","name":"OperatorEx7.java","lastModified":1580181605287,"locationURI":"file:\/D:\/dev\/javachobo\/src\/javachobo\/ch3\/OperatorEx7.java"},{"path":"\/javabook\/src\/javabook\/ch12","parentWorkspace":"D:\/dev\/yoshino","name":"MCUI.java","lastModified":1581473836197,"locationURI":"file:\/D:\/dev\/yoshino\/javabook\/src\/javabook\/ch12\/MCUI.java"},{"path":"\/javabook\/src\/javabook\/c11","parentWorkspace":"D:\/dev","name":"IOtes.java","lastModified":1580795232350,"locationURI":"file:\/D:\/dev\/javabook\/src\/javabook\/c11\/IOtes.java"},{"path":"\/test\/src\/GUItes","parentWorkspace":"D:\/dev","name":"Bgtes.java","lastModified":1581046167978,"locationURI":"file:\/D:\/dev\/test\/src\/GUItes\/Bgtes.java"},{"path":"\/osawa\/src\/mimina","parentWorkspace":"D:\/dev","name":"babo.java","lastModified":1580454036644,"locationURI":"file:\/D:\/dev\/osawa\/src\/mimina\/babo.java"},{"path":"\/javabook\/src\/javabook\/ch7","parentWorkspace":"D:\/dev","name":"C7ex7Cl.java","lastModified":1581326106679,"locationURI":"file:\/D:\/dev\/javabook\/src\/javabook\/ch7\/C7ex7Cl.java"},{"path":"\/javachobo\/src\/javachobo\/ch14","parentWorkspace":"D:\/dev\/yoshino","name":"Lamdex3.java","lastModified":1581403375983,"locationURI":"file:\/D:\/dev\/yoshino\/javachobo\/src\/javachobo\/ch14\/Lamdex3.java"},{"path":"\/osawa\/src\/mimina","parentWorkspace":"D:\/dev","name":"aho.java","lastModified":1580892157301,"locationURI":"file:\/D:\/dev\/osawa\/src\/mimina\/aho.java"},{"path":"\/javabook\/src\/javabook\/c6","parentWorkspace":"D:\/dev","name":"Ch6Ex7.java","lastModified":1580889278124,"locationURI":"file:\/D:\/dev\/javabook\/src\/javabook\/c6\/Ch6Ex7.java"},{"path":"\/test\/src\/test\/g","parentWorkspace":"D:\/dev","name":"Tvtes4.java","lastModified":1580441327768,"locationURI":"file:\/D:\/dev\/test\/src\/test\/g\/Tvtes4.java"},{"path":"\/javabook\/src\/javabook\/c6","parentWorkspace":"D:\/dev","name":"Ch6Ex5.java","lastModified":1580887426603,"locationURI":"file:\/D:\/dev\/javabook\/src\/javabook\/c6\/Ch6Ex5.java"},{"path":"\/javachobo\/src\/javachobo\/ch3","parentWorkspace":"D:\/dev","name":"OperatorEx5.java","lastModified":1580181307772,"locationURI":"file:\/D:\/dev\/javachobo\/src\/javachobo\/ch3\/OperatorEx5.java"},{"path":"\/test\/src\/test","parentWorkspace":"D:\/dev","name":"wtx.java","lastModified":1581296269022,"locationURI":"file:\/D:\/dev\/test\/src\/test\/wtx.java"},{"path":"\/javachobo\/src\/javachobo\/ch13","parentWorkspace":"D:\/dev\/yoshino","name":"Tex6.java","lastModified":1581394385860,"locationURI":"file:\/D:\/dev\/yoshino\/javachobo\/src\/javachobo\/ch13\/Tex6.java"},{"path":"\/javachobo\/src\/javachobo\/ch13","parentWorkspace":"D:\/dev\/yoshino","name":"Tex11.java","lastModified":1581397790827,"locationURI":"file:\/D:\/dev\/yoshino\/javachobo\/src\/javachobo\/ch13\/Tex11.java"},{"path":"\/javabook\/src\/javabook\/c5","parentWorkspace":"D:\/dev","name":"IShop.java","lastModified":1580695944159,"locationURI":"file:\/D:\/dev\/javabook\/src\/javabook\/c5\/IShop.java"},{"path":"\/javachobo\/src\/javachobo\/ch3","parentWorkspace":"D:\/dev","name":"OperatorEx1.java","lastModified":1580181025875,"locationURI":"file:\/D:\/dev\/javachobo\/src\/javachobo\/ch3\/OperatorEx1.java"},{"path":"\/javachobo\/src\/javachobo\/ch15","parentWorkspace":"D:\/dev","name":"DOS1.java","lastModified":1581312879494,"locationURI":"file:\/D:\/dev\/javachobo\/src\/javachobo\/ch15\/DOS1.java"},{"path":"\/javachobo\/src\/javachobo\/ch14","parentWorkspace":"D:\/dev\/yoshino","name":"Lamdex1.java","lastModified":1581402309509,"locationURI":"file:\/D:\/dev\/yoshino\/javachobo\/src\/javachobo\/ch14\/Lamdex1.java"},{"path":"\/javachobo\/src\/javachobo\/ch6","parentWorkspace":"D:\/dev","name":"Clac.java","lastModified":1580439890963,"locationURI":"file:\/D:\/dev\/javachobo\/src\/javachobo\/ch6\/Clac.java"},{"path":"\/javabook\/src\/javabook\/c5","parentWorkspace":"D:\/dev","name":"SmartTV.java","lastModified":1580696773996,"locationURI":"file:\/D:\/dev\/javabook\/src\/javabook\/c5\/SmartTV.java"},{"path":"\/javachobo\/src\/javachobo\/ch3","parentWorkspace":"D:\/dev","name":"OperatorEx9.java","lastModified":1580182343248,"locationURI":"file:\/D:\/dev\/javachobo\/src\/javachobo\/ch3\/OperatorEx9.java"},{"path":"\/javachobo\/src\/javachobo\/ch13","parentWorkspace":"D:\/dev\/yoshino","name":"Tex9.java","lastModified":1581397954898,"locationURI":"file:\/D:\/dev\/yoshino\/javachobo\/src\/javachobo\/ch13\/Tex9.java"},{"path":"\/javabook\/src\/javabook\/c8","parentWorkspace":"D:\/dev","name":"Ex6.java","lastModified":1580801016102,"locationURI":"file:\/D:\/dev\/javabook\/src\/javabook\/c8\/Ex6.java"},{"path":"\/javabook\/src\/javabook\/ch11","parentWorkspace":"D:\/dev\/yoshino","name":"C11ex5.java","lastModified":1581384667035,"locationURI":"file:\/D:\/dev\/yoshino\/javabook\/src\/javabook\/ch11\/C11ex5.java"},{"path":"\/test\/src\/bob","parentWorkspace":"D:\/dev","name":"EvenMoham.java","lastModified":1580965707918,"locationURI":"file:\/D:\/dev\/test\/src\/bob\/EvenMoham.java"},{"path":"\/javachobo\/src\/javachobo\/ch13","parentWorkspace":"D:\/dev\/yoshino","name":"Tex10.java","lastModified":1581396815846,"locationURI":"file:\/D:\/dev\/yoshino\/javachobo\/src\/javachobo\/ch13\/Tex10.java"},{"path":"\/javachobo\/src\/javachobo\/ch6","parentWorkspace":"D:\/dev","name":"Tvtes2.java","lastModified":1580437207668,"locationURI":"file:\/D:\/dev\/javachobo\/src\/javachobo\/ch6\/Tvtes2.java"},{"path":"\/javabook\/src\/javabook\/c8","parentWorkspace":"D:\/dev","name":"Ex2.java","lastModified":1580797428019,"locationURI":"file:\/D:\/dev\/javabook\/src\/javabook\/c8\/Ex2.java"},{"path":"\/javabook\/src\/javabook\/ch7","parentWorkspace":"D:\/dev","name":"C7ex7Clt.java","lastModified":1581391235839,"locationURI":"file:\/D:\/dev\/javabook\/src\/javabook\/ch7\/C7ex7Clt.java"},{"path":"\/vavo\/src\/main\/java\/com\/baba\/boyo","parentWorkspace":"D:\/dev","name":"HomeController.java","lastModified":1581321118185,"locationURI":"file:\/D:\/dev\/vavo\/src\/main\/java\/com\/baba\/boyo\/HomeController.java"},{"path":"\/osawa\/src\/mimina","parentWorkspace":"D:\/dev","name":"GUItes.java","lastModified":1580270671991,"locationURI":"file:\/D:\/dev\/osawa\/src\/mimina\/GUItes.java"},{"path":"\/javabook\/src\/javabook\/c6","parentWorkspace":"D:\/dev","name":"Ch6Ex8.java","lastModified":1580889010724,"locationURI":"file:\/D:\/dev\/javabook\/src\/javabook\/c6\/Ch6Ex8.java"},{"path":"\/javachobo\/src\/javachobo\/ch13","parentWorkspace":"D:\/dev\/yoshino","name":"Tex1.java","lastModified":1581393391572,"locationURI":"file:\/D:\/dev\/yoshino\/javachobo\/src\/javachobo\/ch13\/Tex1.java"},{"path":"\/javachobo\/src\/javachobo\/ch3","parentWorkspace":"D:\/dev","name":"OperatorEx11.java","lastModified":1580182343295,"locationURI":"file:\/D:\/dev\/javachobo\/src\/javachobo\/ch3\/OperatorEx11.java"},{"path":"\/javachobo\/src\/javachobo\/ch11","parentWorkspace":"D:\/dev","name":"Alstex1.java","lastModified":1581043043486,"locationURI":"file:\/D:\/dev\/javachobo\/src\/javachobo\/ch11\/Alstex1.java"},{"path":"\/test\/src\/test\/g","parentWorkspace":"D:\/dev","name":"Tvtes3.java","lastModified":1580441317361,"locationURI":"file:\/D:\/dev\/test\/src\/test\/g\/Tvtes3.java"},{"path":"\/javabook\/src\/javabook\/ch9","parentWorkspace":"D:\/dev","name":"Cex1.java","lastModified":1580979548586,"locationURI":"file:\/D:\/dev\/javabook\/src\/javabook\/ch9\/Cex1.java"},{"path":"\/javabook\/src\/javabook\/c5","parentWorkspace":"D:\/dev","name":"ShopLanch.java","lastModified":1580700083181,"locationURI":"file:\/D:\/dev\/javabook\/src\/javabook\/c5\/ShopLanch.java"},{"path":"\/javabook\/src\/javabook\/c11","parentWorkspace":"D:\/dev","name":"Ex3.java","lastModified":1580788485947,"locationURI":"file:\/D:\/dev\/javabook\/src\/javabook\/c11\/Ex3.java"},{"path":"\/javabook\/src\/javabook\/ch11","parentWorkspace":"D:\/dev\/yoshino","name":"C11ex9.java","lastModified":1581390525739,"locationURI":"file:\/D:\/dev\/yoshino\/javabook\/src\/javabook\/ch11\/C11ex9.java"},{"path":"\/javabook\/src\/javabook\/c6","parentWorkspace":"D:\/dev","name":"Ch6Ex4.java","lastModified":1580881317822,"locationURI":"file:\/D:\/dev\/javabook\/src\/javabook\/c6\/Ch6Ex4.java"},{"path":"\/test\/src\/GUItes","parentWorkspace":"D:\/dev","name":"Elsanna.java","lastModified":1580868446175,"locationURI":"file:\/D:\/dev\/test\/src\/GUItes\/Elsanna.java"},{"path":"\/javabook\/src\/javabook\/c5","parentWorkspace":"D:\/dev","name":"CellPhone.java","lastModified":1580696615753,"locationURI":"file:\/D:\/dev\/javabook\/src\/javabook\/c5\/CellPhone.java"},{"path":"\/javachobo\/src\/javachobo\/ch13","parentWorkspace":"D:\/dev\/yoshino","name":"Tex8.java","lastModified":1581397951640,"locationURI":"file:\/D:\/dev\/yoshino\/javachobo\/src\/javachobo\/ch13\/Tex8.java"},{"path":"\/test\/src\/test\/g","parentWorkspace":"D:\/dev","name":"Tvtes.java","lastModified":1580441356078,"locationURI":"file:\/D:\/dev\/test\/src\/test\/g\/Tvtes.java"},{"path":"\/javachobo\/src\/javachobo\/ch3","parentWorkspace":"D:\/dev","name":"OperatorEx3.java","lastModified":1580181160159,"locationURI":"file:\/D:\/dev\/javachobo\/src\/javachobo\/ch3\/OperatorEx3.java"},{"path":"\/javabook\/src\/javabook\/c8","parentWorkspace":"D:\/dev","name":"Ex5.java","lastModified":1580800094592,"locationURI":"file:\/D:\/dev\/javabook\/src\/javabook\/c8\/Ex5.java"},{"path":"\/javachobo\/src\/javachobo\/ch6","parentWorkspace":"D:\/dev","name":"Clacfn.java","lastModified":1580439879984,"locationURI":"file:\/D:\/dev\/javachobo\/src\/javachobo\/ch6\/Clacfn.java"},{"path":"\/javabook\/src\/javabook\/ch7","parentWorkspace":"D:\/dev","name":"C7ex7.java","lastModified":1581325036999,"locationURI":"file:\/D:\/dev\/javabook\/src\/javabook\/ch7\/C7ex7.java"},{"path":"\/javabook\/src\/javabook\/c6","parentWorkspace":"D:\/dev","name":"Ch6Ex11.java","lastModified":1580955380988,"locationURI":"file:\/D:\/dev\/javabook\/src\/javabook\/c6\/Ch6Ex11.java"},{"path":"\/javabook\/src\/javabook\/ch7","parentWorkspace":"D:\/dev","name":"C7ex2.java","lastModified":1581300618407,"locationURI":"file:\/D:\/dev\/javabook\/src\/javabook\/ch7\/C7ex2.java"},{"path":"\/javabook\/src\/javabook\/ch5","parentWorkspace":"D:\/dev","name":"Hi.java","lastModified":1580690429867,"locationURI":"file:\/D:\/dev\/javabook\/src\/javabook\/ch5\/Hi.java"},{"path":"\/javabook\/src\/javabook\/ch11","parentWorkspace":"D:\/dev\/yoshino","name":"Myf.java","lastModified":1581399481678,"locationURI":"file:\/D:\/dev\/yoshino\/javabook\/src\/javabook\/ch11\/Myf.java"},{"path":"\/osawa\/src\/mimina","parentWorkspace":"D:\/dev","name":"Ladi.java","lastModified":1580449171607,"locationURI":"file:\/D:\/dev\/osawa\/src\/mimina\/Ladi.java"},{"path":"\/javabook\/src\/javabook\/c6","parentWorkspace":"D:\/dev","name":"Ch6Ex1.java","lastModified":1580881313909,"locationURI":"file:\/D:\/dev\/javabook\/src\/javabook\/c6\/Ch6Ex1.java"},{"path":"\/javachobo\/src\/javachobo\/ch14","parentWorkspace":"D:\/dev\/yoshino","name":"Lamdex5.java","lastModified":1581404852093,"locationURI":"file:\/D:\/dev\/yoshino\/javachobo\/src\/javachobo\/ch14\/Lamdex5.java"},{"path":"\/javabook\/src\/javabook\/c5","parentWorkspace":"D:\/dev","name":"MyShop.java","lastModified":1580703279592,"locationURI":"file:\/D:\/dev\/javabook\/src\/javabook\/c5\/MyShop.java"},{"path":"\/test\/src\/test","parentWorkspace":"D:\/dev","name":"Lam.java","lastModified":1581321117923,"locationURI":"file:\/D:\/dev\/test\/src\/test\/Lam.java"},{"path":"\/javachobo\/src\/javachobo\/ch3","parentWorkspace":"D:\/dev","name":"OperatorEx12.java","lastModified":1580183072505,"locationURI":"file:\/D:\/dev\/javachobo\/src\/javachobo\/ch3\/OperatorEx12.java"},{"path":"\/javachobo\/src\/javachobo\/ch13","parentWorkspace":"D:\/dev\/yoshino","name":"Tex2.java","lastModified":1581393646263,"locationURI":"file:\/D:\/dev\/yoshino\/javachobo\/src\/javachobo\/ch13\/Tex2.java"},{"path":"\/javachobo\/src\/javachobo\/ch6","parentWorkspace":"D:\/dev","name":"Tvtes.java","lastModified":1580436930982,"locationURI":"file:\/D:\/dev\/javachobo\/src\/javachobo\/ch6\/Tvtes.java"},{"path":"\/test\/src\/GUItes","parentWorkspace":"D:\/dev","name":"Webrd.java","lastModified":1581046280540,"locationURI":"file:\/D:\/dev\/test\/src\/GUItes\/Webrd.java"},{"path":"\/test\/src\/test\/g","parentWorkspace":"D:\/dev","name":"Tvtes2.java","lastModified":1580441312013,"locationURI":"file:\/D:\/dev\/test\/src\/test\/g\/Tvtes2.java"},{"path":"\/javabook\/src\/javabook\/c11","parentWorkspace":"D:\/dev","name":"Ex2.java","lastModified":1580782335323,"locationURI":"file:\/D:\/dev\/javabook\/src\/javabook\/c11\/Ex2.java"},{"path":"\/javabook\/src\/javabook\/c6","parentWorkspace":"D:\/dev","name":"Ch6Ex3.java","lastModified":1580883934081,"locationURI":"file:\/D:\/dev\/javabook\/src\/javabook\/c6\/Ch6Ex3.java"},{"path":"\/javabook\/src\/javabook\/ch11","parentWorkspace":"D:\/dev\/yoshino","name":"C11ex8.java","lastModified":1581390230385,"locationURI":"file:\/D:\/dev\/yoshino\/javabook\/src\/javabook\/ch11\/C11ex8.java"},{"path":"\/test\/src\/test\/g","parentWorkspace":"D:\/dev","name":"Tvst.java","lastModified":1580802323191,"locationURI":"file:\/D:\/dev\/test\/src\/test\/g\/Tvst.java"},{"path":"\/javabook\/src\/javabook\/ch11","parentWorkspace":"D:\/dev\/yoshino","name":"C11ex6.java","lastModified":1581387592308,"locationURI":"file:\/D:\/dev\/yoshino\/javabook\/src\/javabook\/ch11\/C11ex6.java"},{"path":"\/vavo\/src\/main\/webapp\/WEB-INF\/views","parentWorkspace":"D:\/dev\/yoshino","name":"logck.jsp","lastModified":1581483638074,"locationURI":"file:\/D:\/dev\/yoshino\/vavo\/src\/main\/webapp\/WEB-INF\/views\/logck.jsp"},{"path":"\/test\/src\/test\/g","parentWorkspace":"D:\/dev","name":"Ex01.java","lastModified":1580348899477,"locationURI":"file:\/D:\/dev\/test\/src\/test\/g\/Ex01.java"},{"path":"\/javabook\/src\/javabook\/ch12","parentWorkspace":"D:\/dev\/yoshino","name":"MCserver.java","lastModified":1581478490199,"locationURI":"file:\/D:\/dev\/yoshino\/javabook\/src\/javabook\/ch12\/MCserver.java"},{"path":"\/javabook\/src\/javabook\/c8","parentWorkspace":"D:\/dev","name":"Ex3.java","lastModified":1580796602209,"locationURI":"file:\/D:\/dev\/javabook\/src\/javabook\/c8\/Ex3.java"},{"path":"\/test\/src\/bob","parentWorkspace":"D:\/dev","name":"Menu.java","lastModified":1581390001386,"locationURI":"file:\/D:\/dev\/test\/src\/bob\/Menu.java"},{"path":"\/javachobo\/src\/javachobo\/ch6","parentWorkspace":"D:\/dev","name":"Tv.java","lastModified":1580437520022,"locationURI":"file:\/D:\/dev\/javachobo\/src\/javachobo\/ch6\/Tv.java"},{"path":"\/javachobo\/src\/javachobo\/ch15","parentWorkspace":"D:\/dev","name":"DOS.java","lastModified":1581313197352,"locationURI":"file:\/D:\/dev\/javachobo\/src\/javachobo\/ch15\/DOS.java"},{"path":"\/javabook\/src\/javabook\/ch7","parentWorkspace":"D:\/dev","name":"C7ex5.java","lastModified":1581303682497,"locationURI":"file:\/D:\/dev\/javabook\/src\/javabook\/ch7\/C7ex5.java"},{"path":"\/javabook\/src\/javabook\/c3","parentWorkspace":"D:\/dev","name":"Ex3_8.java","lastModified":1580197684862,"locationURI":"file:\/D:\/dev\/javabook\/src\/javabook\/c3\/Ex3_8.java"},{"path":"\/javabook\/src\/javabook\/ch7","parentWorkspace":"D:\/dev","name":"C7ex4.java","lastModified":1581302842262,"locationURI":"file:\/D:\/dev\/javabook\/src\/javabook\/ch7\/C7ex4.java"},{"path":"\/javabook\/src\/javabook\/c11","parentWorkspace":"D:\/dev","name":"MyExp.java","lastModified":1580783387273,"locationURI":"file:\/D:\/dev\/javabook\/src\/javabook\/c11\/MyExp.java"},{"path":"\/javachobo\/src\/javachobo\/ch15","parentWorkspace":"D:\/dev","name":"DIS.java","lastModified":1581313264694,"locationURI":"file:\/D:\/dev\/javachobo\/src\/javachobo\/ch15\/DIS.java"},{"path":"\/javabook\/src\/javabook\/ch7","parentWorkspace":"D:\/dev","name":"C7ex1.java","lastModified":1581299494503,"locationURI":"file:\/D:\/dev\/javabook\/src\/javabook\/ch7\/C7ex1.java"},{"path":"\/javabook\/src\/javabook\/c5","parentWorkspace":"D:\/dev","name":"Product.java","lastModified":1580700409250,"locationURI":"file:\/D:\/dev\/javabook\/src\/javabook\/c5\/Product.java"},{"path":"\/javachobo\/src\/javachobo\/ch13","parentWorkspace":"D:\/dev\/yoshino","name":"Tex7.java","lastModified":1581394591381,"locationURI":"file:\/D:\/dev\/yoshino\/javachobo\/src\/javachobo\/ch13\/Tex7.java"},{"path":"\/javabook\/src\/javabook\/ch11","parentWorkspace":"D:\/dev\/yoshino","name":"C11ex7.java","lastModified":1581389566949,"locationURI":"file:\/D:\/dev\/yoshino\/javabook\/src\/javabook\/ch11\/C11ex7.java"},{"path":"\/javachobo\/src\/javachobo\/ch6","parentWorkspace":"D:\/dev","name":"Tvtes4.java","lastModified":1580438636912,"locationURI":"file:\/D:\/dev\/javachobo\/src\/javachobo\/ch6\/Tvtes4.java"},{"path":"\/javabook\/src\/javabook\/c8","parentWorkspace":"D:\/dev","name":"Ex4.java","lastModified":1580866555373,"locationURI":"file:\/D:\/dev\/javabook\/src\/javabook\/c8\/Ex4.java"},{"path":"\/test\/src\/test\/g","parentWorkspace":"D:\/dev","name":"Tvfn.java","lastModified":1580440707456,"locationURI":"file:\/D:\/dev\/test\/src\/test\/g\/Tvfn.java"},{"path":"\/test\/src\/bob","parentWorkspace":"D:\/dev","name":"Grp.java","lastModified":1581398843149,"locationURI":"file:\/D:\/dev\/test\/src\/bob\/Grp.java"},{"path":"\/javachobo\/src\/javachobo\/ch13","parentWorkspace":"D:\/dev\/yoshino","name":"Tex3.java","lastModified":1581393895277,"locationURI":"file:\/D:\/dev\/yoshino\/javachobo\/src\/javachobo\/ch13\/Tex3.java"},{"path":"\/javachobo\/src\/javachobo\/ch3","parentWorkspace":"D:\/dev","name":"OperatorEx13.java","lastModified":1580779992914,"locationURI":"file:\/D:\/dev\/javachobo\/src\/javachobo\/ch3\/OperatorEx13.java"},{"path":"\/javabook\/src\/javabook\/ch9","parentWorkspace":"D:\/dev","name":"Cex3.java","lastModified":1581040387353,"locationURI":"file:\/D:\/dev\/javabook\/src\/javabook\/ch9\/Cex3.java"},{"path":"\/javabook\/src\/javabook\/c5","parentWorkspace":"D:\/dev","name":"PayType.java","lastModified":1580696459136,"locationURI":"file:\/D:\/dev\/javabook\/src\/javabook\/c5\/PayType.java"},{"path":"\/javabook\/src\/javabook\/c11","parentWorkspace":"D:\/dev","name":"Ex1.java","lastModified":1580788483430,"locationURI":"file:\/D:\/dev\/javabook\/src\/javabook\/c11\/Ex1.java"}]}